cb_translator/__init__.py
cb_translator/cli.py
cb_translator/core.py
cb_translator/services/__init__.py
cb_translator/services/azure.py
Cube_Translator-0.1.0.dist-info/METADATA
Cube_Translator-0.1.0.dist-info/WHEEL
Cube_Translator-0.1.0.dist-info/entry_points.txt
Cube_Translator-0.1.0.dist-info/top_level.txt
Cube_Translator-0.1.0.dist-info/RECORD
