Metadata-Version: 2.1
Name: Cube-Translator
Version: 0.1.0
Summary: Traslate subtitles from one language to another
Author: Cube Estrada
License: UNKNOWN
Platform: UNKNOWN
Requires-Dist: pysrt
Requires-Dist: requests
